ytfs/__init__.py
ytfs/__main__.py
ytfs/actions.py
ytfs/range_t.py
ytfs/stor.py
ytfs/ytfs.py
ytfs-0.99a5.dist-info/DESCRIPTION.rst
ytfs-0.99a5.dist-info/METADATA
ytfs-0.99a5.dist-info/RECORD
ytfs-0.99a5.dist-info/WHEEL
ytfs-0.99a5.dist-info/entry_points.txt
ytfs-0.99a5.dist-info/metadata.json
ytfs-0.99a5.dist-info/top_level.txt
