Metadata-Version: 2.0
Name: ytfs
Version: 0.99a5
Summary: YouTube File System
Home-page: https://github.com/rasguanabana/ytfs
Author: Adrian Włosiak
Author-email: adwlosiakh@gmail.com
License: MIT
Keywords: youtube fuse filesystem
Platform: UNKNOWN
Classifier: Development Status :: 3 - Alpha
Classifier: Environment :: Console
Classifier: Intended Audience :: End Users/Desktop
Classifier: License :: OSI Approved :: MIT License
Classifier: Operating System :: Unix
Classifier: Programming Language :: Python :: 3 :: Only
Classifier: Programming Language :: Python :: 3
Classifier: Programming Language :: Python :: 3.4
Classifier: Programming Language :: Python :: 3.5
Classifier: Topic :: System :: Filesystems
Requires-Dist: fusepy
Requires-Dist: requests
Requires-Dist: youtube-dl
